MANIFEST.in
README.md
setup.py
anthill/environment/__init__.py
anthill/environment/admin.py
anthill/environment/handler.py
anthill/environment/options.py
anthill/environment/server.py
anthill/environment/model/__init__.py
anthill/environment/model/application.py
anthill/environment/model/environment.py
anthill/environment/sql/application_versions.sql
anthill/environment/sql/applications.sql
anthill/environment/sql/environments.sql
anthill/environment/sql/scheme.sql
anthill_environment.egg-info/PKG-INFO
anthill_environment.egg-info/SOURCES.txt
anthill_environment.egg-info/dependency_links.txt
anthill_environment.egg-info/namespace_packages.txt
anthill_environment.egg-info/not-zip-safe
anthill_environment.egg-info/requires.txt
anthill_environment.egg-info/top_level.txt