Metadata-Version: 1.0
Name: anthill-environment
Version: 0.2
Summary: An application environment service for Anthill platform
Home-page: https://github.com/anthill-platform/anthill-environment
Author: desertkun
Author-email: desertkun@gmail.com
License: MIT
Platform: UNKNOWN
